libprg-3.data/data/share/doc/libprg/README.rst
libprg-3.data/scripts/prg
prg/broker.py
prg/disk.py
prg/error.py
prg/find.py
prg/object.py
prg/run.py
prg/thread.py
prg/mods/__init__.py
prg/mods/cmd.py
prg/mods/err.py
prg/mods/fnd.py
prg/mods/log.py
prg/mods/mbx.py
prg/mods/mod.py
prg/mods/shp.py
prg/mods/tdo.py
prg/mods/thr.py
libprg-3.dist-info/METADATA
libprg-3.dist-info/WHEEL
libprg-3.dist-info/top_level.txt
libprg-3.dist-info/zip-safe
libprg-3.dist-info/RECORD
