Metadata-Version: 2.1
Name: libprg
Version: 3
Summary: program library
Author-email: libprg <libbotx@gmail.com>
License: Public Domain
Project-URL: home, https://pypi.org/project/libprg
Project-URL: bugs, https://github.com/botlibx/libprg/issues
Project-URL: source, https://github.com/botlibx/libprg
Classifier: Development Status :: 3 - Alpha
Classifier: License :: Public Domain
Classifier: Operating System :: Unix
Classifier: Programming Language :: Python
Classifier: Topic :: Utilities
